Workbook

Sheet Параметры
A1: Параметр | B1: Значение
A2: Часовая ставка (₽) | B2: 5000
A3: Проект | B3: Grammy
A4: Описание | B4: Telegram-бот продажи доступа в закрытые каналы + админ-панель
A6: Изменение ставки в B2 автоматически пересчитает все стоимости на других листах.

Sheet Сводная
A1: ID | B1: Модуль | C1: Backend | D1: Frontend | E1: Design | F1: DevOps | G1: QA | H1: Всего, ч | I1: Стоимость, ₽ | J1: Пакеты
A2: M01 | B2: Платформа и инфраструктура | C2: 0 | D2: 0 | E2: 0 | F2: 5 | G2: 0 | H2: 5 | I2: =H2*Параметры!$B$2 | J2: base, standard, premium
A3: M02 | B3: Аутентификация и RBAC | C3: 4 | D3: 2 | E3: 2 | F3: 0 | G3: 1 | H3: 9 | I3: =H3*Параметры!$B$2 | J3: base, standard, premium
A4: M03 | B4: Каталог: продукты, каналы, боты | C4: 4 | D4: 4 | E4: 1 | F4: 0 | G4: 4 | H4: 13 | I4: =H4*Параметры!$B$2 | J4: base, standard, premium
A5: M04 | B5: Пользователи и first-touch | C5: 3 | D5: 2 | E5: 1 | F5: 0 | G5: 0 | H5: 6 | I5: =H5*Параметры!$B$2 | J5: base, standard, premium
A6: M05 | B6: Заявки (Leads) | C6: 2 | D6: 2 | E6: 1 | F6: 0 | G6: 0 | H6: 5 | I6: =H6*Параметры!$B$2 | J6: base, standard, premium
A7: M06 | B7: Платежи и подписки | C7: 6 | D7: 3 | E7: 1 | F7: 0 | G7: 4 | H7: 14 | I7: =H7*Параметры!$B$2 | J7: base, standard, premium
A8: M07 | B8: Воронки прогрева (Студия) | C8: 5 | D8: 12 | E8: 9 | F8: 0 | G8: 2 | H8: 28 | I8: =H8*Параметры!$B$2 | J8: standard, premium
A9: M08 | B9: Лидмагниты | C9: 2 | D9: 2 | E9: 1 | F9: 0 | G9: 0 | H9: 5 | I9: =H9*Параметры!$B$2 | J9: standard, premium
A10: M09 | B10: Точки входа: tracking-ссылки и кодовые слова | C10: 5 | D10: 3 | E10: 1 | F10: 0 | G10: 0 | H10: 9 | I10: =H10*Параметры!$B$2 | J10: standard, premium
A11: M10 | B11: Аналитика и метрики | C11: 4 | D11: 10 | E11: 2 | F11: 0 | G11: 0 | H11: 16 | I11: =H11*Параметры!$B$2 | J11: standard, premium
A12: M11 | B12: Telegram-бот (aiogram, multi-bot) | C12: 7 | D12: 0 | E12: 1 | F12: 0 | G12: 3 | H12: 11 | I12: =H12*Параметры!$B$2 | J12: base, standard, premium
A13: M12 | B13: Админ-панель UI/UX (база) | C13: 0 | D13: 8 | E13: 4 | F13: 0 | G13: 1 | H13: 13 | I13: =H13*Параметры!$B$2 | J13: base, standard, premium
... A17: M16 | B17: QA: тесты и CI/CD | C17: 0 | D17: 0 | E17: 0 | F17: 2 | G17: 10 | H17: 12 | I17: =H17*Параметры!$B$2 | J17: premium
A18: ИТОГО | B18: Все модули (полная комплектация) | C18: =SUM(C2:C17) | D18: =SUM(D2:D17) | E18: =SUM(E2:E17) | F18: =SUM(F2:F17) | G18: =SUM(G2:G17) | H18: =SUM(H2:H17) | I18: =H18*Параметры!$B$2

Sheet Детализация
A1: Модуль ТЗ | B1: Задача | C1: Backend | D1: Frontend | E1: Design | F1: DevOps | G1: QA | H1: Всего, ч | I1: Стоимость, ₽
A2: M01. Платформа и инфраструктура
A3: M01 | B3: Docker Compose: db / backend / admin / nginx / certbot | F3: 3 | H3: 3 | I3: =H3*Параметры!$B$2
A4: M01 | B4: Healthcheck Postgres + /api/healthz endpoint | H4: 0 | I4: =H4*Параметры!$B$2
A5: M01 | B5: Nginx-конфиг с SSL termination и проксированием | F5: 1 | H5: 1 | I5: =H5*Параметры!$B$2
A6: M01 | B6: Certbot webroot + auto-renew | F6: 1 | H6: 1 | I6: =H6*Параметры!$B$2
A7: M01 | B7: Cron daily docker cleanup | H7: 0 | I7: =H7*Параметры!$B$2
A8: M01 | B8: .env / .env.example / документация переменных | H8: 0 | I8: =H8*Параметры!$B$2
B9: Итого M01 | C9: 0 | D9: 0 | E9: 0 | F9: 5 | G9: 0 | H9: 5 | I9: =H9*Параметры!$B$2
A10: M02. Аутентификация и RBAC
A11: M02 | B11: Backend: модель Admin + миграция + bcrypt-утилиты | C11: 1 | H11: 1 | I11: =H11*Параметры!$B$2
A12: M02 | B12: Endpoint /auth/login + JWT + cookie + rate-limit | C12: 1 | G12: 1 | H12: 2 | I12: =H12*Параметры!$B$2
A13: M02 | B13: Endpoint /auth/me + /auth/logout + смена пароля | C13: 1 | H13: 1 | I13: =H13*Параметры!$B$2
A14: M02 | B14: Dependency current_admin + require_role(*) | C14: 1 | H14: 1 | I14: =H14*Параметры!$B$2
A15: M02 | B15: Frontend: /login форма + redirect логика | D15: 1 | E15: 1 | H15: 2 | I15: =H15*Параметры!$B$2
A16: M02 | B16: Frontend: auth-check в layout, fetch-обёртка с 401 | D16: 1 | H16: 1 | I16: =H16*Параметры!$B$2
A17: M02 | B17: UX: пустые поля, ошибки, состояние «вошёл» | E17: 1 | H17: 1 | I17: =H17*Параметры!$B$2
B18: Итого M02 | C18: 4 | D18: 2 | E18: 2 | F18: 0 | G18: 1 | H18: 9 | I18: =H18*Параметры!$B$2
A19: M03. Каталог: продукты, каналы, боты
A20: M03 | B20: Backend: модели Bot/Channel/Product + миграции | C20: 1 | H20: 1 | I20: =H20*Параметры!$B$2
A21: M03 | B21: Backend API /bots (CRUD, getMe-валидация, sync polling) | C21: 1 | G21: 1 | H21: 2 | I21: =H21*Параметры!$B$2
A22: M03 | B22: Backend API /channels (CRUD, проверка прав бота) | C22: 1 | G22: 1 | H22: 2 | I22: =H22*Параметры!$B$2
A23: M03 | B23: Backend API /products (CRUD, code-unique, collision-check) | C23: 1 | G23: 1 | H23: 2 | I23: =H23*Параметры!$B$2
A24: M03 | B24: Frontend: страница /bots | D24: 1 | H24: 1 | I24: =H24*Параметры!$B$2
A25: M03 | B25: Frontend: страница /channels | D25: 1 | H25: 1 | I25: =H25*Параметры!$B$2
A26: M03 | B26: Frontend: страница /products + детали + ссылки | D26: 2 | G26: 1 | H26: 3 | I26: =H26*Параметры!$B$2
A27: M03 | B27: Дизайн: формы CRUD, пустые состояния, badges | E27: 1 | H27: 1 | I27: =H27*Параметры!$B$2
B28: Итого M03 | C28: 4 | D28: 4 | E28: 1 | F28: 0 | G28: 4 | H28: 13 | I28: =H28*Параметры!$B$2
A29: M04. Пользователи и first-touch
A30: M04 | B30: Backend: модель User + first_* поля + миграции | C30: 2 | H30: 2 | I30: =H30*Параметры!$B$2
A31: M04 | B31: Backend: идемпотентная функция _set_first_touch | H31: 0 | I31: =H31*Параметры!$B$2
A32: M04 | B32: Backend API /users (поиск, профиль с JOIN) | C32: 1 | H32: 1 | I32: =H32*Параметры!$B$2
A33: M04 | B33: Frontend: /users со строкой поиска | D33: 1 | H33: 1 | I33: =H33*Параметры!$B$2
A34: M04 | B34: Frontend: /users/[id] с тремя вкладками истории | D34: 1 | H34: 1 | I34: =H34*Параметры!$B$2
A35: M04 | B35: Дизайн: профиль пользователя | E35: 1 | H35: 1 | I35: =H35*Параметры!$B$2
B36: Итого M04 | C36: 3 | D36: 2 | E36: 1 | F36: 0 | G36: 0 | H36: 6 | I36: =H36*Параметры!$B$2
A37: M05. Заявки (Leads)
A38: M05 | B38: Backend: модель Lead + миграция + FSM | C38: 1 | H38: 1 | I38: =H38*Параметры!$B$2
A39: M05 | B39: Backend API /leads (CRUD, фильтр, экспорт CSV) | C39: 1 | H39: 1 | I39: =H39*Параметры!$B$2
A40: M05 | B40: Frontend: /leads с табами + badge в sidebar | D40: 1 | H40: 1 | I40: =H40*Параметры!$B$2
A41: M05 | B41: Frontend: /leads/[id] | D41: 1 | H41: 1 | I41: =H41*Параметры!$B$2
A42: M05 | B42: Дизайн: лид-карточка и таблица | E42: 1 | H42: 1 | I42: =H42*Параметры!$B$2
B43: Итого M05 | C43: 2 | D43: 2 | E43: 1 | F43: 0 | G43: 0 | H43: 5 | I43: =H43*Параметры!$B$2
A44: M06. Платежи и подписки
A45: M06 | B45: Backend: модели Payment + Subscription + миграции | C45: 1 | H45: 1 | I45: =H45*Параметры!$B$2
A46: M06 | B46: Backend: сервис subscriptions.grant_for_payment | C46: 1 | G46: 1 | H46: 2 | I46: =H46*Параметры!$B$2
A47: M06 | B47: Backend: revoke/extend + интеграция aiogram (kick, invite) | C47: 1 | G47: 1 | H47: 2 | I47: =H47*Параметры!$B$2
A48: M06 | B48: Backend API /payments + /subscriptions | C48: 1 | G48: 1 | H48: 2 | I48: =H48*Параметры!$B$2
A49: M06 | B49: Backend: worker expire_due (APScheduler hourly) | C49: 1 | H49: 1 | I49: =H49*Параметры!$B$2
A50: M06 | B50: Backend: Telegram Payments — PreCheckout + SuccessfulPayment | C50: 1 | G50: 1 | H50: 2 | I50: =H50*Параметры!$B$2
A51: M06 | B51: Frontend: /payments + UserPicker | D51: 2 | H51: 2 | I51: =H51*Параметры!$B$2
A52: M06 | B52: Frontend: /subscriptions с действиями revoke/extend | D52: 1 | H52: 1 | I52: =H52*Параметры!$B$2
A53: M06 | B53: Дизайн: формы платежа, статусы подписок | E53: 1 | H53: 1 | I53: =H53*Параметры!$B$2
B54: Итого M06 | C54: 6 | D54: 3 | E54: 1 | F54: 0 | G54: 4 | H54: 14 | I54: =H54*Параметры!$B$2
A55: M07. Воронки прогрева (Студия)
A56: M07 | B56: Backend: модели Funnel/FunnelStep/FunnelEntry/ScheduledMessage + миграции | C56: 1 | H56: 1 | I56: =H56*Параметры!$B$2
A57: M07 | B57: Backend: сервис FunnelsService (start_for_user, cancel_entry) | C57: 1 | G57: 1 | H57: 2 | I57: =H57*Параметры!$B$2
A58: M07 | B58: Backend API /funnels (CRUD, reorder) | C58: 1 | H58: 1 | I58: =H58*Параметры!$B$2
A59: M07 | B59: Backend API /funnels/{id}/entries | C59: 1 | H59: 1 | I59: =H59*Параметры!$B$2
A60: M07 | B60: Backend: worker scheduled_messages (батч, шаблонизация, отмена) | C60: 1 | G60: 1 | H60: 2 | I60: =H60*Параметры!$B$2
A61: M07 | B61: Backend: cancel_on_payment интеграция | H61: 0 | I61: =H61*Параметры!$B$2
A62: M07 | B62: Frontend: Студия воронок — section 1 (параметры) с auto-save | D62: 1 | H62: 1 | I62: =H62*Параметры!$B$2
A63: M07 | B63: Frontend: Студия — section 2 (шаги, drag-n-drop) | D63: 2 | H63: 2 | I63: =H63*Параметры!$B$2
A64: M07 | B64: Frontend: Студия — section 3 (точки входа + EntryPointsSection) | D64: 1 | H64: 1 | I64: =H64*Параметры!$B$2
A65: M07 | B65: Frontend: Студия — section 4 (запуск + warnings) | D65: 1 | H65: 1 | I65: =H65*Параметры!$B$2
A66: M07 | B66: Frontend: компонент RichTextEditor (тулбар, хоткеи, undo) | D66: 2 | H66: 2 | I66: =H66*Параметры!$B$2
A67: M07 | B67: Frontend: компонент TelegramPreview (HTML-whitelist, рендер) | D67: 1 | H67: 1 | I67: =H67*Параметры!$B$2
A68: M07 | B68: Frontend: ObservableTestPanel + SSE | D68: 1 | H68: 1 | I68: =H68*Параметры!$B$2
A69: M07 | B69: Frontend: SafetyWarning + ActiveFunnelConfirm | D69: 1 | H69: 1 | I69: =H69*Параметры!$B$2
A70: M07 | B70: Frontend: ButtonsEditor | D70: 1 | H70: 1 | I70: =H70*Параметры!$B$2
A71: M07 | B71: Frontend: FunnelWizard (4-шаговый диалог) | D71: 1 | H71: 1 | I71: =H71*Параметры!$B$2
A72: M07 | B72: Дизайн: Студия — флагманский UX, 4 секции, превью, drag-n-drop | E72: 8 | H72: 8 | I72: =H72*Параметры!$B$2
A73: M07 | B73: Дизайн: UX-сценарии правки и тестирования | E73: 1 | H73: 1 | I73: =H73*Параметры!$B$2
B74: Итого M07 | C74: 5 | D74: 12 | E74: 9 | F74: 0 | G74: 2 | H74: 28 | I74: =H74*Параметры!$B$2
A75: M08. Лидмагниты
A76: M08 | B76: Backend: модель LeadMagnet + миграция | H76: 0 | I76: =H76*Параметры!$B$2
A77: M08 | B77: Backend: сервис LeadMagnetsService (upload, send, type-detect) | C77: 1 | H77: 1 | I77: =H77*Параметры!$B$2
A78: M08 | B78: Backend API /lead-magnets (CRUD + upload) | C78: 1 | H78: 1 | I78: =H78*Параметры!$B$2
A79: M08 | B79: Frontend: /lead-magnets таблица | D79: 1 | H79: 1 | I79: =H79*Параметры!$B$2
A80: M08 | B80: Frontend: QuickLeadMagnetUpload (drag-n-drop + прогресс) | D80: 1 | H80: 1 | I80: =H80*Параметры!$B$2
A81: M08 | B81: Дизайн: drop-zone, preview, типы файлов | E81: 1 | H81: 1 | I81: =H81*Параметры!$B$2
B82: Итого M08 | C82: 2 | D82: 2 | E82: 1 | F82: 0 | G82: 0 | H82: 5 | I82: =H82*Параметры!$B$2
A83: M09. Точки входа: tracking-ссылки и кодовые слова
A84: M09 | B84: Backend: модели TrackingLink + FunnelTrigger + миграции (unique index) | C84: 3 | H84: 3 | I84: =H84*Параметры!$B$2
A85: M09 | B85: Backend: сервис TrackingLinksService (slug-gen, collision-check) | C85: 1 | H85: 1 | I85: =H85*Параметры!$B$2
A86: M09 | B86: Backend: сервис FunnelTriggersService (case-insensitive) | H86: 0 | I86: =H86*Параметры!$B$2
A87: M09 | B87: Backend API /tracking-links + /funnel-triggers | C87: 1 | H87: 1 | I87: =H87*Параметры!$B$2
A88: M09 | B88: Backend: интеграция click_count / unique_users в боте | H88: 0 | I88: =H88*Параметры!$B$2
A89: M09 | B89: Frontend: блок «Точки входа» в Студии + копирование с тостом | D89: 1 | H89: 1 | I89: =H89*Параметры!$B$2
A90: M09 | B90: Frontend: страница /funnel-triggers | D90: 1 | H90: 1 | I90: =H90*Параметры!$B$2
A91: M09 | B91: Frontend: страница /products/[id] — ссылки на продукт | D91: 1 | H91: 1 | I91: =H91*Параметры!$B$2
A92: M09 | B92: Дизайн: модалки создания ссылки, slug-preview | E92: 1 | H92: 1 | I92: =H92*Параметры!$B$2
B93: Итого M09 | C93: 5 | D93: 3 | E93: 1 | F93: 0 | G93: 0 | H93: 9 | I93: =H93*Параметры!$B$2
A94: M10. Аналитика и метрики
A95: M10 | B95: Backend: модель индексов под аналитику + миграция | H95: 0 | I95: =H95*Параметры!$B$2
A96: M10 | B96: Backend: /stats/overview (10+ COUNT/SUM) | H96: 0 | I96: =H96*Параметры!$B$2
A97: M10 | B97: Backend: /stats/health с warnings (8+ диагностик) | C97: 1 | H97: 1 | I97: =H97*Параметры!$B$2
A98: M10 | B98: Backend: /stats/timeline (date_trunc, last/first-touch, dimensions) | C98: 1 | H98: 1 | I98: =H98*Параметры!$B$2
A99: M10 | B99: Backend: /stats/funnels/summary (single-query JOIN, DISTINCT) | C99: 1 | H99: 1 | I99: =H99*Параметры!$B$2
A100: M10 | B100: Backend: /stats/funnels/{id}/conversion (per-step метрики) | C100: 1 | H100: 1 | I100: =H100*Параметры!$B$2
...

Sheet Пакеты
A1: Пакет | B1: Описание | C1: Состав (модули) | D1: Всего, ч | E1: Стоимость, ₽
A2: Базовый (MVP) | B2: Минимально жизнеспособный продукт: можно подключить ботов и каналы, продавать продукты, обрабатывать заявки и платежи вручную, выдавать доступ. Без воронок, без полноценной аналитики, без observability. | C2: M01, M02, M03, M04, M05, M06, M11, M12, M13 | D2: 80 | E2: =D2*Параметры!$B$2
A3: Стандарт | B3: Базовый + автоматизация и аналитика: воронки прогрева, tracking-ссылки и UTM, лидмагниты, страница аналитики с фильтрами и графиками, наблюдаемость с алертами. Готовый production-инструмент инфобиз-команды. | C3: M01, M02, M03, M04, M05, M06, M07, M08, M09, M10, M11, M12, M13, M15 | D3: 145 | E3: =D3*Параметры!$B$2
A4: Премиум | B4: Стандарт + полноценный compliance и QA: журнал действий с маскированием секретов, полное покрытие тестами (backend ~470, frontend ~28, e2e 6), CI/CD с 5 jobs, pre-commit, security-сканирование. | C4: M01, M02, M03, M04, M05, M06, M07, M08, M09, M10, M11, M12, M13, M14, M15, M16 | D4: 163 | E4: =D4*Параметры!$B$2

Sheet Матрица
A1: Модуль | B1: Базовый (MVP) | C1: Стандарт | D1: Премиум
A2: M01. Платформа и инфраструктура | B2: ✓ | C2: ✓ | D2: ✓
A3: M02. Аутентификация и RBAC | B3: ✓ | C3: ✓ | D3: ✓
A4: M03. Каталог: продукты, каналы, боты | B4: ✓ | C4: ✓ | D4: ✓
A5: M04. Пользователи и first-touch | B5: ✓ | C5: ✓ | D5: ✓
A6: M05. Заявки (Leads) | B6: ✓ | C6: ✓ | D6: ✓
A7: M06. Платежи и подписки | B7: ✓ | C7: ✓ | D7: ✓
A8: M07. Воронки прогрева (Студия) | C8: ✓ | D8: ✓
A9: M08. Лидмагниты | C9: ✓ | D9: ✓
A10: M09. Точки входа: tracking-ссылки и кодовые слова | C10: ✓ | D10: ✓
A11: M10. Аналитика и метрики | C11: ✓ | D11: ✓
A12: M11. Telegram-бот (aiogram, multi-bot) | B12: ✓ | C12: ✓ | D12: ✓
A13: M12. Админ-панель UI/UX (база) | B13: ✓ | C13: ✓ | D13: ✓
A14: M13. Брендинг и SEO | B14: ✓ | C14: ✓ | D14: ✓
A15: M14. Аудит-журнал | D15: ✓
A16: M15. Observability и алерты | C16: ✓ | D16: ✓
A17: M16. QA: тесты и CI/CD | D17: ✓
